LICENSE
MANIFEST.in
setup.py
raptor/__init__.py
raptor/build.py
raptor/models.py
raptor/publisher.py
raptor/remote.py
raptor/repo.py
raptor/supervisor_utils.py
raptor/utils.py
raptor.egg-info/PKG-INFO
raptor.egg-info/SOURCES.txt
raptor.egg-info/dependency_links.txt
raptor.egg-info/entry_points.txt
raptor.egg-info/requires.txt
raptor.egg-info/top_level.txt
raptor/balancer/__init__.py
raptor/balancer/base.py
raptor/balancer/dummy.py
raptor/balancer/nginx.py
raptor/balancer/stingray.py
raptor/balancer/stingray_pool.wsdl
raptor/balancer/varnish.py
raptor/templates/precise.lxc
raptor/templates/proc.conf
raptor/templates/proc.sh
raptor/templates/start_proc.sh
raptor/tests/__init__.py
raptor/tests/test_build.py
raptor/tests/test_models.py
raptor/tests/test_publisher.py
raptor/tests/test_repos.py
raptor/tests/test_utils.py
raptor/uptester/uptester
raptor/uptester/uptester.go