Metadata-Version: 1.0
Name: raptor
Version: 2.15.2
Summary: Libraries and command line tools for deploying with Velociraptor
Home-page: UNKNOWN
Author: Brent Tubbs
Author-email: brent.tubbs@gmail.com
License: UNKNOWN
Platform: UNKNOWN
